Metadata-Version: 2.1
Name: gimbal-api
Version: 0.0.1
Requires-Dist: torch-mlir-gml
Requires-Dist: torch
